butachanrl/ActorCriticAgent.py
butachanrl/DQNAgent.py
butachanrl/ExperienceReplay.py
butachanrl/Network.py
butachanrl/RL.py
butachanrl/Utilities.py
butachanrl/__init__.py
butachanrl/preprocess.py
butachanrl-0.1.1.dist-info/LICENSE
butachanrl-0.1.1.dist-info/METADATA
butachanrl-0.1.1.dist-info/WHEEL
butachanrl-0.1.1.dist-info/top_level.txt
butachanrl-0.1.1.dist-info/RECORD
