Metadata-Version: 2.1
Name: butachanrl
Version: 0.1.1
Author: ThawTar
Author-email: mr.thaw.tar1990@gmail.com
License: MIT
License-File: LICENSE
Requires-Dist: gymnasium ==0.28.1
Requires-Dist: numpy >=1.25.2
Requires-Dist: pandas ==2.0.3
Requires-Dist: matplotlib ==3.7.2
Requires-Dist: torch ==2.0.1
Requires-Dist: tqdm
